setup.py
pure_pcapy/__init__.py
pure_pcapy.egg-info/PKG-INFO
pure_pcapy.egg-info/SOURCES.txt
pure_pcapy.egg-info/dependency_links.txt
pure_pcapy.egg-info/top_level.txt